aedat-2.2.0.dist-info/RECORD
aedat-2.2.0.dist-info/WHEEL
aedat-2.2.0.dist-info/METADATA
aedat-2.2.0.dist-info/licenses/LICENSE
aedat/__init__.py
aedat/aedat.cpython-311-darwin.so
