Metadata-Version: 2.3
Name: aedat
Version: 2.2.0
Requires-Dist: numpy >=1.26
License-File: LICENSE
Summary: A fast AEDAT4 decoder with an underlying Rust implementation
Author: International Centre for Neuromorphic Systems, Alexandre Marcireau
Requires-Python: >=3.9
Project-URL: homepage, https://github.com/neuromorphicsystems/aedat/
Project-URL: repository, https://github.com/neuromorphicsystems/aedat/
Project-URL: documentation, https://github.com/neuromorphicsystems/aedat/
